Metadata-Version: 2.3
Name: did-webvh
Version: 1.0.0
Summary: This repository includes Python libraries for working with `did:webvh` (did:web + Verified History) DID documents and the underlying log format.
License: Apache-2.0
Requires-Python: >= 3.10, <4
Classifier: License :: OSI Approved :: Apache Software License
Classifier: Programming Language :: Python :: 3
Classifier: Programming Language :: Python :: 3.10
Classifier: Programming Language :: Python :: 3.11
Classifier: Programming Language :: Python :: 3.12
Classifier: Programming Language :: Python :: 3.13
Requires-Dist: aiohttp (>=3.10.5,<4.0.0)
Requires-Dist: aries-askar (>=0.3.2)
Requires-Dist: base58 (>=2.1.0,<2.2.0)
Requires-Dist: jsoncanon (>=0.2.3,<0.3.0)
Requires-Dist: multiformats (>=0.3.1,<0.4.0)
